Main/__init__.py
base/Memoria.py
gerador/Palavra.py
gerarPalavraa-0.0.2.dist-info/LICENSE
gerarPalavraa-0.0.2.dist-info/METADATA
gerarPalavraa-0.0.2.dist-info/WHEEL
gerarPalavraa-0.0.2.dist-info/top_level.txt
gerarPalavraa-0.0.2.dist-info/RECORD
