Metadata-Version: 2.1
Name: gerarPalavraa
Version: 0.0.2
Summary: Pacote python para gerar, armazenar e exibir palavras dissilabas
Home-page: UNKNOWN
Author: Pedro Benitah Vieira Sanchez de Melo
Author-email: pedrobenitah@gmail.com
License: MIT License
Keywords: Pacote
Platform: UNKNOWN
License-File: LICENSE
